none_aware/__init__.py
none_aware/maybe.py
none_aware-0.0.2.dist-info/LICENSE
none_aware-0.0.2.dist-info/METADATA
none_aware-0.0.2.dist-info/WHEEL
none_aware-0.0.2.dist-info/top_level.txt
none_aware-0.0.2.dist-info/RECORD
