Metadata-Version: 2.1
Name: none-aware
Version: 0.0.2
Summary: Package provided none-aware wrapper for none-safety object manipulation.
Home-page: https://github.com/dkotlyar/python-none-aware
Author: Dmitry Kotlyar
Author-email: dm.kotlyar@yandex.ru
License: MIT
Platform: UNKNOWN
Classifier: Programming Language :: Python :: 3.8
Classifier: License :: OSI Approved :: MIT License
Classifier: Operating System :: OS Independent
Requires-Python: >=3.6
License-File: LICENSE
